visualize_heapq/__init__.py
visualize_heapq-0.0.3.dist-info/METADATA
visualize_heapq-0.0.3.dist-info/WHEEL
visualize_heapq-0.0.3.dist-info/licenses/LICENSE
visualize_heapq-0.0.3.dist-info/RECORD
