Metadata-Version: 2.3
Name: visualize_heapq
Version: 0.0.3
Summary: A package that visualizes heapq heaps
Project-URL: Homepage, https://github.com/zlliu246/visualize_heapq
Project-URL: Issues, https://github.com/zlliu246/visualize_heapq/issues
Author-email: Liu Zuo Lin <zlliu246@gmail.com>
Classifier: License :: OSI Approved :: MIT License
Classifier: Operating System :: OS Independent
Classifier: Programming Language :: Python :: 3
Requires-Python: >=3.8
Requires-Dist: print-btree
